[
	{
		"name": "Tarasume",
		"leaderName": "Jenkin",
		"adjective": ["tarasume"],
		"startBias": ["Forest"],
		"preferredVictoryType": "Domination",
		
		"startIntroPart1": "We love the jungle, but we also love to rule the world.",
		"startIntroPart2": "Braatatata!!!",
		
		"declaringWar": "Prepare to attack!",
		"attacked": "You want to play? lets play.",
		"defeated": "i.. ",
		"introduction": "The forest is dark, yet its beautiful.",
		
		"neutralHello": "How are you doing?",
		"neutralLetsHearIt": ["Go on.","What do you say?","You may begin."],
		"neutralNo": ["We absolutely refuse.","No!","I refuse. Respect my decision"],
		"neutralYes": ["Very good.","Of course, yes.","That is very good."],

		"hateHello": "Who dare to walk on my authority?",
		"hateLetsHearIt": ["Speak!","What do you say?","Go on."],
		"hateNo": ["That is not possible!","We are not agreeing to that!","I beg your pardon?"],
		"hateYes": ["That is fine.","That is good enough.","Very well..."],
		
		"afterPeace": "Very well, all that fighting was getting boring anyway.",
		"tradeRequest": "We bestow you the honor of this trade offer.",

		"outerColor": [16,16,16],
		"innerColor": [255,200,200],
		"unique": "MANIFEST_DESTINY",
		"cities": ["Tarasume City","Q'Nuit","Q'Baljjiher","Q'Akrrila","Q'Egghead","Q'Terra","Q'Vulsivar","Q'Umbra","Q'Aerlar",
			"Q'Phoenix","Q'Jetto","Q'Pistolare","Q'Gume","Q'Mamars","Q'Drynamon","Q'Mazea","Q'Einer","Q'Bulcrax","Q'Honaiwrat",
			"Q'Ujjilyears","Q'Vahars","Q'Cyperia","Q'Hide","Q'Bhoknais","Qho'Qru","Q'Dateatz","Q'Elnad","Q'Izien","Qol'Ell",
			"Q'Dhihien","Q'Naquiel","Q'Ugneon","Q'Straquks","Q'Nulptr","Q'Ohfahl"]
	}
]
